[
  {
    "imageUrl": "https://goshort.filmchief.com/f/Still_3_Wo%20die%20wilden%20Bienen%20wohnen%20_%20Pascal%20Kohler.jpg?rmode=pad&width=383&height=287&format=webp",
    "title": "Shorts @ De Bastei",
    "date": "2025-03-29",
    "start": "10:00",
    "end": "17:00",
    "type": "EXPO"
  },
  {
    "imageUrl": "https://goshort.filmchief.com/f/Still_3_Wo%20die%20wilden%20Bienen%20wohnen%20_%20Pascal%20Kohler.jpg?rmode=pad&width=383&height=287&format=webp",
    "title": "Shorts @ De Bastei",
    "date": "2025-03-30",
    "start": "10:00",
    "end": "17:00",
    "type": "EXPO"
  },
  {
    "imageUrl": "https://goshort.filmchief.com/f/Still_3_Wo%20die%20wilden%20Bienen%20wohnen%20_%20Pascal%20Kohler.jpg?rmode=pad&width=383&height=287&format=webp",
    "title": "Shorts @ De Bastei",
    "date": "2025-03-31",
    "start": "10:00",
    "end": "17:00",
    "type": "EXPO"
  },
  {
    "imageUrl": "https://goshort.filmchief.com/f/Still_3_Wo%20die%20wilden%20Bienen%20wohnen%20_%20Pascal%20Kohler.jpg?rmode=pad&width=383&height=287&format=webp",
    "title": "Shorts @ De Bastei",
    "date": "2025-04-01",
    "start": "10:00",
    "end": "17:00",
    "type": "EXPO"
  },
  {
    "imageUrl": "https://goshort.filmchief.com/f/Still_3_Wo%20die%20wilden%20Bienen%20wohnen%20_%20Pascal%20Kohler.jpg?rmode=pad&width=383&height=287&format=webp",
    "title": "Shorts @ De Bastei",
    "date": "2025-04-02",
    "start": "10:00",
    "end": "17:00",
    "type": "EXPO"
  },
  {
    "imageUrl": "https://goshort.filmchief.com/f/GS24%20-%20Randprogramma%20[Emiel%20Janssen]%20-110%20(1).jpg?rmode=pad&width=383&height=287&format=webp",
    "title": "Virtual Reality",
    "date": "2025-04-02",
    "start": "12:00",
    "end": "22:00",
    "type": "EXPO"
  },
  {
    "imageUrl": "https://goshort.filmchief.com/f/data-garden-screenshot1%20(1).jpg?rmode=pad&width=383&height=287&format=webp",
    "title": "Game Expo",
    "date": "2025-04-02",
    "start": "12:00",
    "end": "22:00",
    "type": "EXPO"
  },
  {
    "imageUrl": "https://goshort.filmchief.com/f/Club%20Goud%20x%20Go%20Short.jpg?rmode=pad&width=383&height=287&format=webp",
    "title": "Club Goud x Go Short 1",
    "date": "2025-04-02",
    "start": "13:30",
    "end": "15:00",
    "type": "SHORTS"
  },
  {
    "imageUrl": "https://goshort.filmchief.com/f/GV_2609A5835%20(1).jpg?rmode=pad&width=383&height=287&format=webp",
    "title": "Short Surprise: Family Edition",
    "date": "2025-04-02",
    "start": "14:00",
    "end": "16:00",
    "type": "SHORTS"
  },
  {
    "imageUrl": "https://goshort.filmchief.com/f/THE%20GIRL%20WITH%20THE%20OCCUPIED%20EYES_Img_1%20(1).jpg?rmode=pad&width=383&height=287&format=webp",
    "title": "Family Shorts 4+",
    "date": "2025-04-02",
    "start": "14:45",
    "end": "15:45",
    "type": "SHORTS"
  },
  {
    "imageUrl": "https://goshort.filmchief.com/f/GV_2609A5835%20(1).jpg?rmode=pad&width=383&height=287&format=webp",
    "title": "Short Surprise: Family Edition",
    "date": "2025-04-02",
    "start": "16:00",
    "end": "18:00",
    "type": "SHORTS"
  },
  {
    "imageUrl": "https://goshort.filmchief.com/f/img-64db61da94d2c%20(1).jpg?rmode=pad&width=383&height=287&format=webp",
    "title": "Oscar Shorts - Fiction",
    "date": "2025-04-02",
    "start": "16:30",
    "end": "18:15",
    "type": "SHORTS"
  },
  {
    "imageUrl": "https://goshort.filmchief.com/f/Industry%20drinks%20(1).jpg?rmode=pad&width=383&height=287&format=webp",
    "title": "Industry drinks",
    "date": "2025-04-02",
    "start": "17:00",
    "end": "18:30",
    "type": "PARTY / DRINKS"
  },
  {
    "imageUrl": "https://goshort.filmchief.com/f/Still_1%20(10).jpg?rmode=pad&width=383&height=287&format=webp",
    "title": "Dutch Competition 1: Different Realities",
    "date": "2025-04-02",
    "start": "18:45",
    "end": "20:15",
    "type": "SHORTS"
  },
  {
    "imageUrl": "https://goshort.filmchief.com/f/Movies%20that%20Matter%20x%20Go%20Short.jpg?rmode=pad&width=383&height=287&format=webp",
    "title": "Movies That Matter x Go Short: On Censorship 16+",
    "date": "2025-04-02",
    "start": "19:00",
    "end": "20:30",
    "type": "SHORTS"
  },
  {
    "imageUrl": "https://goshort.filmchief.com/f/WTW_01%20(1).jpg?rmode=pad&width=383&height=287&format=webp",
    "title": "Oscar Shorts - Animation (NL subtitled)",
    "date": "2025-04-02",
    "start": "19:15",
    "end": "20:45",
    "type": "SHORTS"
  },
  {
    "imageUrl": "https://goshort.filmchief.com/f/IMG_9055.jpg?rmode=pad&width=383&height=287&format=webp",
    "title": "VPRO Cinema Pubquiz",
    "date": "2025-04-02",
    "start": "20:00",
    "end": "22:30",
    "type": "EXPO"
  },
  {
    "imageUrl": "https://goshort.filmchief.com/f/2%20(73).png?rmode=pad&width=383&height=287&format=webp",
    "title": "New Arrivals Competition 1: We're In This Together",
    "date": "2025-04-02",
    "start": "21:00",
    "end": "22:30",
    "type": "SHORTS"
  },
  {
    "imageUrl": "https://goshort.filmchief.com/f/still%201%20955%20excl%20(1).jpg?rmode=pad&width=383&height=287&format=webp",
    "title": "Reflections: De mismatch op de woningmarkt",
    "date": "2025-04-02",
    "start": "21:15",
    "end": "22:45",
    "type": "SHORTS"
  },
  {
    "imageUrl": "https://goshort.filmchief.com/f/Can%20You%20Hear%20Me%20-%20Still%202%20(4).jpg?rmode=pad&width=383&height=287&format=webp",
    "title": "European Competition 1: Frozen in Time",
    "date": "2025-04-02",
    "start": "21:15",
    "end": "22:45",
    "type": "SHORTS"
  },
  {
    "imageUrl": "https://goshort.filmchief.com/f/Still_3_Wo%20die%20wilden%20Bienen%20wohnen%20_%20Pascal%20Kohler.jpg?rmode=pad&width=383&height=287&format=webp",
    "title": "Shorts @ De Bastei",
    "date": "2025-04-03",
    "start": "10:00",
    "end": "17:00",
    "type": "EXPO"
  },
  {
    "imageUrl": "https://goshort.filmchief.com/f/GS24%20-%20Randprogramma%20[Emiel%20Janssen]%20-110%20(1).jpg?rmode=pad&width=383&height=287&format=webp",
    "title": "Virtual Reality",
    "date": "2025-04-03",
    "start": "12:00",
    "end": "22:00",
    "type": "EXPO"
  },
  {
    "imageUrl": "https://goshort.filmchief.com/f/data-garden-screenshot1%20(1).jpg?rmode=pad&width=383&height=287&format=webp",
    "title": "Game Expo",
    "date": "2025-04-03",
    "start": "12:00",
    "end": "22:00",
    "type": "EXPO"
  },
  {
    "imageUrl": "https://goshort.filmchief.com/f/Club%20Goud%20x%20Go%20Short%20(1).jpg?rmode=pad&width=383&height=287&format=webp",
    "title": "Club Goud x Go Short 2",
    "date": "2025-04-03",
    "start": "13:30",
    "end": "15:00",
    "type": "SHORTS"
  },
  {
    "imageUrl": "https://goshort.filmchief.com/f/close-up-sculptor-artist-creating-sculpture-face-with-clay-colored-background%20(1).jpg?rmode=pad&width=383&height=287&format=webp",
    "title": "Workshop Worldbuilding: Hybrid Worlding",
    "date": "2025-04-03",
    "start": "16:00",
    "end": "18:00",
    "type": "EXPO"
  },
  {
    "imageUrl": "https://goshort.filmchief.com/f/Industry%20drinks%20(1).jpg?rmode=pad&width=383&height=287&format=webp",
    "title": "Industry drinks",
    "date": "2025-04-03",
    "start": "17:00",
    "end": "18:30",
    "type": "PARTY / DRINKS"
  },
  {
    "imageUrl": "https://goshort.filmchief.com/f/CELJADE_CROP-1-4%20(1).png?rmode=pad&width=383&height=287&format=webp",
    "title": "New Arrivals Competition 2: Can I Live Here?",
    "date": "2025-04-03",
    "start": "17:00",
    "end": "18:30",
    "type": "SHORTS"
  },
  {
    "imageUrl": "https://goshort.filmchief.com/f/Their%20Eyes%201%20(1).png?rmode=pad&width=383&height=287&format=webp",
    "title": "European Competition 2: We Stand Together",
    "date": "2025-04-03",
    "start": "17:15",
    "end": "18:45",
    "type": "SHORTS"
  },
  {
    "imageUrl": "https://goshort.filmchief.com/f/18a2240.jpg?rmode=pad&width=383&height=287&format=webp",
    "title": "Film Concert: Betonkust + Palmbomen & Kaito Winse",
    "date": "2025-04-03",
    "start": "19:00",
    "end": "20:15",
    "type": "SHORTS"
  },
  {
    "imageUrl": "https://goshort.filmchief.com/f/Skroll%20Still%20image%203%20(2).jpg?rmode=pad&width=383&height=287&format=webp",
    "title": "Dutch Competition 2: Going in Circles",
    "date": "2025-04-03",
    "start": "19:00",
    "end": "20:30",
    "type": "SHORTS"
  },
  {
    "imageUrl": "https://goshort.filmchief.com/f/88%20(1).png?rmode=pad&width=383&height=287&format=webp",
    "title": "European Competition 3: In Disguise",
    "date": "2025-04-03",
    "start": "19:15",
    "end": "20:45",
    "type": "SHORTS"
  },
  {
    "imageUrl": "https://goshort.filmchief.com/f/img-66d19bed7949c%20(2).jpg?rmode=pad&width=383&height=287&format=webp",
    "title": "Comedy Shorts (NL subtitled)",
    "date": "2025-04-03",
    "start": "19:30",
    "end": "21:00",
    "type": "SHORTS"
  },
  {
    "imageUrl": "https://goshort.filmchief.com/f/MomsMovieStill1%20(2).jpg?rmode=pad&width=383&height=287&format=webp",
    "title": "Radboud Reflects: Familievloggers - je hele jeugd op YouTube (NL spoken)",
    "date": "2025-04-03",
    "start": "20:00",
    "end": "21:00",
    "type": "SHORTS"
  },
  {
    "imageUrl": "https://goshort.filmchief.com/f/Goodbye%20To%20Mercury_film%20still_06%20(1).jpg?rmode=pad&width=383&height=287&format=webp",
    "title": "Music Video Competition",
    "date": "2025-04-03",
    "start": "21:00",
    "end": "22:30",
    "type": "SHORTS"
  },
  {
    "imageUrl": "https://goshort.filmchief.com/f/TFSSW_Still%202_web%20(2).png?rmode=pad&width=383&height=287&format=webp",
    "title": "European Competition 4: Between the Flowers",
    "date": "2025-04-03",
    "start": "21:15",
    "end": "22:45",
    "type": "SHORTS"
  },
  {
    "imageUrl": "https://goshort.filmchief.com/f/MySleeplessFriends_Still1%C2%A9TaraNajdAhmadi+sixpackfilm%20(1).jpg?rmode=pad&width=383&height=287&format=webp",
    "title": "Reflections: Sleepless Nights",
    "date": "2025-04-03",
    "start": "21:30",
    "end": "23:00",
    "type": "SHORTS"
  },
  {
    "imageUrl": "https://goshort.filmchief.com/f/Still%202%20(13).png?rmode=pad&width=383&height=287&format=webp",
    "title": "Late Night: Horror Shorts 16+",
    "date": "2025-04-03",
    "start": "21:30",
    "end": "23:00",
    "type": "SHORTS"
  },
  {
    "imageUrl": "https://goshort.filmchief.com/f/img-6712223e31f0a%20(1).jpg?rmode=pad&width=383&height=287&format=webp",
    "title": "New Arrivals Competition 3: Life Is Like That",
    "date": "2025-04-03",
    "start": "21:30",
    "end": "23:00",
    "type": "SHORTS"
  },
  {
    "imageUrl": "https://goshort.filmchief.com/f/Wet%20Spaghetti.jpg?rmode=pad&width=383&height=287&format=webp",
    "title": "Afterparty Franco James",
    "date": "2025-04-03",
    "start": "22:00",
    "end": "02:00",
    "type": "PARTY / DRINKS"
  },
  {
    "imageUrl": "https://goshort.filmchief.com/f/Still_3_Wo%20die%20wilden%20Bienen%20wohnen%20_%20Pascal%20Kohler.jpg?rmode=pad&width=383&height=287&format=webp",
    "title": "Shorts @ De Bastei",
    "date": "2025-04-04",
    "start": "10:00",
    "end": "17:00",
    "type": "EXPO"
  },
  {
    "imageUrl": "https://goshort.filmchief.com/f/GS24%20-%20Randprogramma%20[Emiel%20Janssen]%20-110%20(1).jpg?rmode=pad&width=383&height=287&format=webp",
    "title": "Virtual Reality",
    "date": "2025-04-04",
    "start": "12:00",
    "end": "22:00",
    "type": "EXPO"
  },
  {
    "imageUrl": "https://goshort.filmchief.com/f/data-garden-screenshot1%20(1).jpg?rmode=pad&width=383&height=287&format=webp",
    "title": "Game Expo",
    "date": "2025-04-04",
    "start": "12:00",
    "end": "22:00",
    "type": "EXPO"
  },
  {
    "imageUrl": "https://goshort.filmchief.com/f/copyright_Majmun_Films%20(1).jpg?rmode=pad&width=383&height=287&format=webp",
    "title": "European Competition 5: Past or Present?",
    "date": "2025-04-04",
    "start": "14:00",
    "end": "15:30",
    "type": "SHORTS"
  },
  {
    "imageUrl": "https://goshort.filmchief.com/f/epoxyparadise_still3%20(1).jpg?rmode=pad&width=383&height=287&format=webp",
    "title": "Go Ahead",
    "date": "2025-04-04",
    "start": "15:00",
    "end": "16:30",
    "type": "SHORTS"
  },
  {
    "imageUrl": "https://goshort.filmchief.com/f/JAN3%20(1).jpg?rmode=pad&width=383&height=287&format=webp",
    "title": "Short Surprise 12+",
    "date": "2025-04-04",
    "start": "15:30",
    "end": "21:00",
    "type": "SHORTS"
  },
  {
    "imageUrl": "https://goshort.filmchief.com/f/1%20(90).jpg?rmode=pad&width=383&height=287&format=webp",
    "title": "New Arrivals Competition 4: The Things I Owned",
    "date": "2025-04-04",
    "start": "15:30",
    "end": "17:00",
    "type": "SHORTS"
  },
  {
    "imageUrl": "https://goshort.filmchief.com/f/Industry%20drinks%20(1).jpg?rmode=pad&width=383&height=287&format=webp",
    "title": "Industry drinks",
    "date": "2025-04-04",
    "start": "17:00",
    "end": "18:30",
    "type": "PARTY / DRINKS"
  },
  {
    "imageUrl": "https://goshort.filmchief.com/f/1%20(95).jpg?rmode=pad&width=383&height=287&format=webp",
    "title": "Showcase: Talent Under the Radar",
    "date": "2025-04-04",
    "start": "17:00",
    "end": "18:30",
    "type": "SHORTS"
  },
  {
    "imageUrl": "https://goshort.filmchief.com/f/ANEETO_Still_01%20(1).png?rmode=pad&width=383&height=287&format=webp",
    "title": "European Competition 6: To (Not) Move On",
    "date": "2025-04-04",
    "start": "17:30",
    "end": "19:00",
    "type": "SHORTS"
  },
  {
    "imageUrl": "https://goshort.filmchief.com/f/The%20Plantriarchy%20-%20Bernice%20Nauta%20&%20GC%20Heemskerk,%20Netherlands,%202024,%20image%202%20(2).jpg?rmode=pad&width=383&height=287&format=webp",
    "title": "Dutch Competition 3: Forgotten Histories",
    "date": "2025-04-04",
    "start": "17:30",
    "end": "19:00",
    "type": "SHORTS"
  },
  {
    "imageUrl": "https://goshort.filmchief.com/f/we%20need%20new%20names1%20(1).png?rmode=pad&width=383&height=287&format=webp",
    "title": "Filmmaker in Focus: Onyeka Igwe",
    "date": "2025-04-04",
    "start": "17:45",
    "end": "19:30",
    "type": "SHORTS"
  },
  {
    "imageUrl": "https://goshort.filmchief.com/f/Sorry_still_02%20(2).jpg?rmode=pad&width=383&height=287&format=webp",
    "title": "25 Years of 48 Hour Film Project",
    "date": "2025-04-04",
    "start": "19:00",
    "end": "20:30",
    "type": "SHORTS"
  },
  {
    "imageUrl": "https://goshort.filmchief.com/f/Garan1%20(1).png?rmode=pad&width=383&height=287&format=webp",
    "title": "European Competition 7: No Way Forward",
    "date": "2025-04-04",
    "start": "19:15",
    "end": "20:45",
    "type": "SHORTS"
  },
  {
    "imageUrl": "https://goshort.filmchief.com/f/Teun%20Peters.jpg?rmode=pad&width=383&height=287&format=webp",
    "title": "Teun Peters x Go Short",
    "date": "2025-04-04",
    "start": "19:30",
    "end": "21:00",
    "type": "SHORTS"
  },
  {
    "imageUrl": "https://goshort.filmchief.com/f/ILIAS%20DEF_FinalGradeMix%20Export-01_03_37_17-Still012%20(2).jpg?rmode=pad&width=383&height=287&format=webp",
    "title": "Showcase: New Producers Academy",
    "date": "2025-04-04",
    "start": "19:30",
    "end": "21:00",
    "type": "SHORTS"
  },
  {
    "imageUrl": "https://goshort.filmchief.com/f/img-673f24b18beb6%20(2).jpg?rmode=pad&width=383&height=287&format=webp",
    "title": "Dutch Competition 4: Be Careful With Me",
    "date": "2025-04-04",
    "start": "20:00",
    "end": "21:30",
    "type": "SHORTS"
  },
  {
    "imageUrl": "https://goshort.filmchief.com/f/CS_Still001%20(1).jpg?rmode=pad&width=383&height=287&format=webp",
    "title": "Filmmaker in Focus: Image Acts - Aylin Kuryel & Firat Yücel",
    "date": "2025-04-04",
    "start": "21:15",
    "end": "23:00",
    "type": "SHORTS"
  },
  {
    "imageUrl": "https://goshort.filmchief.com/f/lasortie_08_rouge2_2_044_%20(1).jpg?rmode=pad&width=383&height=287&format=webp",
    "title": "Late Night: Erotic Shorts 16+",
    "date": "2025-04-04",
    "start": "21:30",
    "end": "23:00",
    "type": "SHORTS"
  },
  {
    "imageUrl": "https://goshort.filmchief.com/f/Wintertuin%20x%20Go%20Short%20(4).jpg?rmode=pad&width=383&height=287&format=webp",
    "title": "Wintertuin x Go Short: All Will Be Ukraine (with Lisa Weeda)",
    "date": "2025-04-04",
    "start": "21:45",
    "end": "23:30",
    "type": "SHORTS"
  },
  {
    "imageUrl": "https://goshort.filmchief.com/f/ThatsHowILoveYou_Still_01%20(1).jpg?rmode=pad&width=383&height=287&format=webp",
    "title": "European Competition 8: Can Magic Be Real?",
    "date": "2025-04-04",
    "start": "22:00",
    "end": "23:30",
    "type": "SHORTS"
  },
  {
    "imageUrl": "https://goshort.filmchief.com/f/Ontwerp%20zonder%20titel.jpg?rmode=pad&width=383&height=287&format=webp",
    "title": "Afterparty De Plak",
    "date": "2025-04-04",
    "start": "23:00",
    "end": "04:00",
    "type": "PARTY / DRINKS"
  },
  {
    "imageUrl": "https://goshort.filmchief.com/f/Still_3_Wo%20die%20wilden%20Bienen%20wohnen%20_%20Pascal%20Kohler.jpg?rmode=pad&width=383&height=287&format=webp",
    "title": "Shorts @ De Bastei",
    "date": "2025-04-05",
    "start": "10:00",
    "end": "17:00",
    "type": "EXPO"
  },
  {
    "imageUrl": "https://goshort.filmchief.com/f/Still_Master_Painter_Dotty_Doertel_03%20(1).jpg?rmode=pad&width=383&height=287&format=webp",
    "title": "LUX Mini x Go Short 2+",
    "date": "2025-04-05",
    "start": "10:30",
    "end": "11:15",
    "type": "SHORTS"
  },
  {
    "imageUrl": "https://goshort.filmchief.com/f/Razeh-del%20Still%203%20(1).jpg?rmode=pad&width=383&height=287&format=webp",
    "title": "European Competition 9: Public Investigations",
    "date": "2025-04-05",
    "start": "11:30",
    "end": "13:00",
    "type": "SHORTS"
  },
  {
    "imageUrl": "https://goshort.filmchief.com/f/GS24%20-%20Randprogramma%20[Emiel%20Janssen]%20-110%20(1).jpg?rmode=pad&width=383&height=287&format=webp",
    "title": "Virtual Reality",
    "date": "2025-04-05",
    "start": "12:00",
    "end": "22:00",
    "type": "EXPO"
  },
  {
    "imageUrl": "https://goshort.filmchief.com/f/data-garden-screenshot1%20(1).jpg?rmode=pad&width=383&height=287&format=webp",
    "title": "Game Expo",
    "date": "2025-04-05",
    "start": "12:00",
    "end": "22:00",
    "type": "EXPO"
  },
  {
    "imageUrl": "https://goshort.filmchief.com/f/Raw%20data.jpg?rmode=pad&width=383&height=287&format=webp",
    "title": "Raw Data: The Origins of Digital Film",
    "date": "2025-04-05",
    "start": "12:45",
    "end": "14:15",
    "type": "SHORTS"
  },
  {
    "imageUrl": "https://goshort.filmchief.com/f/downloaden%20(1).jpg?rmode=pad&width=383&height=287&format=webp",
    "title": "VPRO day",
    "date": "2025-04-05",
    "start": "13:00",
    "end": "16:15",
    "type": "SHORTS"
  },
  {
    "imageUrl": "https://goshort.filmchief.com/f/img-66c9911aa8a6b%20(1).jpg?rmode=pad&width=383&height=287&format=webp",
    "title": "Family Shorts 6+",
    "date": "2025-04-05",
    "start": "13:00",
    "end": "14:15",
    "type": "SHORTS"
  },
  {
    "imageUrl": "https://goshort.filmchief.com/f/Stone%20of%20Destiny%20-%20Still%203%20(2).jpg?rmode=pad&width=383&height=287&format=webp",
    "title": "New Arrivals Competition 5: Let Me Free!",
    "date": "2025-04-05",
    "start": "13:15",
    "end": "14:45",
    "type": "SHORTS"
  },
  {
    "imageUrl": "https://goshort.filmchief.com/f/img-66d6b9889153c%20(2).jpg?rmode=pad&width=383&height=287&format=webp",
    "title": "European Competition 10: Confusing Times",
    "date": "2025-04-05",
    "start": "13:30",
    "end": "15:00",
    "type": "SHORTS"
  },
  {
    "imageUrl": "https://goshort.filmchief.com/f/image%20(5).png?rmode=pad&width=383&height=287&format=webp",
    "title": "From the Philips NXP archives: a Time Capsule of Innovation and Vision",
    "date": "2025-04-05",
    "start": "14:45",
    "end": "16:30",
    "type": "SHORTS"
  },
  {
    "imageUrl": "https://goshort.filmchief.com/f/HouseofBrokenHearts_stills1_72DPI%20(2).jpg?rmode=pad&width=383&height=287&format=webp",
    "title": "Dutch Competition 5: Under the Skin",
    "date": "2025-04-05",
    "start": "14:45",
    "end": "16:15",
    "type": "SHORTS"
  },
  {
    "imageUrl": "https://goshort.filmchief.com/f/And%20Granny%20Would%20Dance%20Maryam%20Mohajer%2002%20(3).jpg?rmode=pad&width=383&height=287&format=webp",
    "title": "European Competition 11: Talking Behind Your Back",
    "date": "2025-04-05",
    "start": "15:15",
    "end": "16:45",
    "type": "SHORTS"
  },
  {
    "imageUrl": "https://goshort.filmchief.com/f/GS24%20-%20Aventurijn%20[Emiel%20Janssen]%20-106.jpg?rmode=pad&width=383&height=287&format=webp",
    "title": "Workshop: Make Your Own TikTok Documentary! 14+",
    "date": "2025-04-05",
    "start": "15:30",
    "end": "18:00",
    "type": "EXPO"
  },
  {
    "imageUrl": "https://goshort.filmchief.com/f/JAN3%20(1).jpg?rmode=pad&width=383&height=287&format=webp",
    "title": "Short Surprise 12+",
    "date": "2025-04-05",
    "start": "16:30",
    "end": "21:00",
    "type": "SHORTS"
  },
  {
    "imageUrl": "https://goshort.filmchief.com/f/MaxColson_Lidar_LondonKnowledge_03%20(2).jpg?rmode=pad&width=383&height=287&format=webp",
    "title": "Reflections: Self-Driving Cars and AI: Road to Nowhere",
    "date": "2025-04-05",
    "start": "16:45",
    "end": "18:30",
    "type": "SHORTS"
  },
  {
    "imageUrl": "https://goshort.filmchief.com/f/Industry%20drinks%20(1).jpg?rmode=pad&width=383&height=287&format=webp",
    "title": "Industry drinks",
    "date": "2025-04-05",
    "start": "17:00",
    "end": "18:30",
    "type": "PARTY / DRINKS"
  },
  {
    "imageUrl": "https://goshort.filmchief.com/f/KafanaNaBalkanu_Still12%20(2).jpg?rmode=pad&width=383&height=287&format=webp",
    "title": "European Audience Favourites 1",
    "date": "2025-04-05",
    "start": "17:15",
    "end": "19:00",
    "type": "SHORTS"
  },
  {
    "imageUrl": "https://goshort.filmchief.com/f/WE3%20(1).jpg?rmode=pad&width=383&height=287&format=webp",
    "title": "Reflections: Artist Films in Transit",
    "date": "2025-04-05",
    "start": "17:15",
    "end": "19:00",
    "type": "SHORTS"
  },
  {
    "imageUrl": "https://goshort.filmchief.com/f/Lasting%20Marks%20-%20still%2001%20-%20kleiner%20(1).jpg?rmode=pad&width=383&height=287&format=webp",
    "title": "Screening the Screen: Desktop Documentary",
    "date": "2025-04-05",
    "start": "17:30",
    "end": "19:00",
    "type": "SHORTS"
  },
  {
    "imageUrl": "https://goshort.filmchief.com/f/L_XAUSA5%20(1).jpg?rmode=pad&width=383&height=287&format=webp",
    "title": "Reflections: Peeling Back Colonial Layers",
    "date": "2025-04-05",
    "start": "19:00",
    "end": "20:45",
    "type": "SHORTS"
  },
  {
    "imageUrl": "https://goshort.filmchief.com/f/IDII_4%20(1).jpg?rmode=pad&width=383&height=287&format=webp",
    "title": "International Highlights 1",
    "date": "2025-04-05",
    "start": "19:30",
    "end": "21:00",
    "type": "SHORTS"
  },
  {
    "imageUrl": "https://goshort.filmchief.com/f/img-66d19bed7949c%20(2).jpg?rmode=pad&width=383&height=287&format=webp",
    "title": "Comedy Shorts (NL subtitled)",
    "date": "2025-04-05",
    "start": "19:30",
    "end": "21:00",
    "type": "SHORTS"
  },
  {
    "imageUrl": "https://goshort.filmchief.com/f/Rubber%20Coated%20Steel%20-%202016%20-%20Film%20Still%20-%20Lawrence%20Abu%20Hamdan%20-%20Courtesy%20of%20the%20artist%20(3).jpg?rmode=pad&width=383&height=287&format=webp",
    "title": "Filmmaker in Focus: Lawrence Abu Hamdan",
    "date": "2025-04-05",
    "start": "21:15",
    "end": "23:00",
    "type": "SHORTS"
  },
  {
    "imageUrl": "https://goshort.filmchief.com/f/img-6762d970e98d3%20(2).jpg?rmode=pad&width=383&height=287&format=webp",
    "title": "Documentary Favourites",
    "date": "2025-04-05",
    "start": "21:30",
    "end": "23:00",
    "type": "SHORTS"
  },
  {
    "imageUrl": "https://goshort.filmchief.com/f/4_1-1-4%20(2).jpg?rmode=pad&width=383&height=287&format=webp",
    "title": "Reflections: iPhone Fever Dreams",
    "date": "2025-04-05",
    "start": "21:30",
    "end": "23:00",
    "type": "SHORTS"
  },
  {
    "imageUrl": "https://goshort.filmchief.com/f/img-67266ac4975f1%20(1).jpg?rmode=pad&width=383&height=287&format=webp",
    "title": "Late Night: Weird Animation 16+",
    "date": "2025-04-05",
    "start": "21:45",
    "end": "23:15",
    "type": "SHORTS"
  },
  {
    "imageUrl": "https://goshort.filmchief.com/f/GS24%20-%20Silent%20Disco%20[Emiel%20Janssen]%20-109%20(1).jpg?rmode=pad&width=383&height=287&format=webp",
    "title": "Afterparty De Onderbroek",
    "date": "2025-04-05",
    "start": "23:00",
    "end": "04:00",
    "type": "PARTY / DRINKS"
  },
  {
    "imageUrl": "https://goshort.filmchief.com/f/Still_3_Wo%20die%20wilden%20Bienen%20wohnen%20_%20Pascal%20Kohler.jpg?rmode=pad&width=383&height=287&format=webp",
    "title": "Shorts @ De Bastei",
    "date": "2025-04-06",
    "start": "10:00",
    "end": "17:00",
    "type": "EXPO"
  },
  {
    "imageUrl": "https://goshort.filmchief.com/f/Still_Master_Painter_Dotty_Doertel_03%20(1).jpg?rmode=pad&width=383&height=287&format=webp",
    "title": "LUX Mini x Go Short 2+",
    "date": "2025-04-06",
    "start": "10:30",
    "end": "11:15",
    "type": "SHORTS"
  },
  {
    "imageUrl": "https://goshort.filmchief.com/f/img-67266ad6e31b8%20(1).jpg?rmode=pad&width=383&height=287&format=webp",
    "title": "Homegrown 1",
    "date": "2025-04-06",
    "start": "12:00",
    "end": "13:30",
    "type": "SHORTS"
  },
  {
    "imageUrl": "https://goshort.filmchief.com/f/GS24%20-%20Randprogramma%20[Emiel%20Janssen]%20-110%20(1).jpg?rmode=pad&width=383&height=287&format=webp",
    "title": "Virtual Reality",
    "date": "2025-04-06",
    "start": "12:00",
    "end": "20:00",
    "type": "EXPO"
  },
  {
    "imageUrl": "https://goshort.filmchief.com/f/data-garden-screenshot1%20(1).jpg?rmode=pad&width=383&height=287&format=webp",
    "title": "Game Expo",
    "date": "2025-04-06",
    "start": "12:00",
    "end": "20:00",
    "type": "EXPO"
  },
  {
    "imageUrl": "https://goshort.filmchief.com/f/GoShort_YoriFotografie-261.jpg?rmode=pad&width=383&height=287&format=webp",
    "title": "Go Short Award Winners 1",
    "date": "2025-04-06",
    "start": "12:45",
    "end": "14:30",
    "type": "SHORTS"
  },
  {
    "imageUrl": "https://goshort.filmchief.com/f/hein_2024_vpro_campagnebeeld%20liggend_%C2%A9pupkin.jpeg?rmode=pad&width=383&height=287&format=webp",
    "title": "VPRO: Achter de schermen bij Hein 10+",
    "date": "2025-04-06",
    "start": "13:30",
    "end": "15:00",
    "type": "SHORTS"
  },
  {
    "imageUrl": "https://goshort.filmchief.com/f/JAN3%20(1).jpg?rmode=pad&width=383&height=287&format=webp",
    "title": "Short Surprise 12+",
    "date": "2025-04-06",
    "start": "14:00",
    "end": "17:30",
    "type": "SHORTS"
  },
  {
    "imageUrl": "https://goshort.filmchief.com/f/2720_Still_03%20(1).jpg?rmode=pad&width=383&height=287&format=webp",
    "title": "International Highlights 2: EFA Nominations",
    "date": "2025-04-06",
    "start": "14:15",
    "end": "15:55",
    "type": "SHORTS"
  },
  {
    "imageUrl": "https://goshort.filmchief.com/f/OZ%20still%203%20(1).jpg?rmode=pad&width=383&height=287&format=webp",
    "title": "Go Short Audience Favorites 1",
    "date": "2025-04-06",
    "start": "15:00",
    "end": "16:45",
    "type": "SHORTS"
  },
  {
    "imageUrl": "https://goshort.filmchief.com/f/KHAYA%20STILLS%201%20(1).png?rmode=pad&width=383&height=287&format=webp",
    "title": "New Rootz Premieres",
    "date": "2025-04-06",
    "start": "16:15",
    "end": "17:45",
    "type": "SHORTS"
  },
  {
    "imageUrl": "https://goshort.filmchief.com/f/MeneerGroenendaal_Still2%20(2).jpg?rmode=pad&width=383&height=287&format=webp",
    "title": "Homegrown 2",
    "date": "2025-04-06",
    "start": "16:30",
    "end": "18:15",
    "type": "SHORTS"
  },
  {
    "imageUrl": "https://goshort.filmchief.com/f/Nun-still-02%20(2).jpg?rmode=pad&width=383&height=287&format=webp",
    "title": "European Audience Favourites 2 16+",
    "date": "2025-04-06",
    "start": "17:15",
    "end": "19:00",
    "type": "SHORTS"
  },
  {
    "imageUrl": "https://goshort.filmchief.com/f/512x512_photo5%20(1).jpg?rmode=pad&width=383&height=287&format=webp",
    "title": "Reflections: Facial Recognition: Who Owns Your Face?",
    "date": "2025-04-06",
    "start": "18:45",
    "end": "20:30",
    "type": "SHORTS"
  },
  {
    "imageUrl": "https://goshort.filmchief.com/f/GoShort_YoriFotografie-261%20(1).jpg?rmode=pad&width=383&height=287&format=webp",
    "title": "Go Short Award Winners 2",
    "date": "2025-04-06",
    "start": "19:15",
    "end": "20:45",
    "type": "SHORTS"
  },
  {
    "imageUrl": "https://goshort.filmchief.com/f/Sven%20Ratzke.jpg?rmode=pad&width=383&height=287&format=webp",
    "title": "Sven Ratzke x Go Short",
    "date": "2025-04-06",
    "start": "19:30",
    "end": "21:00",
    "type": "SHORTS"
  },
  {
    "imageUrl": "https://goshort.filmchief.com/f/acrobats%20still%20copy%20(2).jpg?rmode=pad&width=383&height=287&format=webp",
    "title": "A Brave New Perspective",
    "date": "2025-04-06",
    "start": "19:30",
    "end": "21:10",
    "type": "SHORTS"
  },
  {
    "imageUrl": "https://goshort.filmchief.com/f/OZ%20still%203%20(2).jpg?rmode=pad&width=383&height=287&format=webp",
    "title": "Go Short Audience Favorites 2",
    "date": "2025-04-06",
    "start": "21:00",
    "end": "22:45",
    "type": "SHORTS"
  },
  {
    "imageUrl": "https://goshort.filmchief.com/f/img-64db61da94d2c%20(1).jpg?rmode=pad&width=383&height=287&format=webp",
    "title": "Oscar Shorts - Fiction",
    "date": "2025-04-06",
    "start": "21:15",
    "end": "23:00",
    "type": "SHORTS"
  }
]
